remote_detector/__init__.py
remote_detector/cli.py
remote_detector/detector.py
remote_detector/erp.py
remote_detector/logger.py
remote_detector-0.1.2.dist-info/METADATA
remote_detector-0.1.2.dist-info/WHEEL
remote_detector-0.1.2.dist-info/entry_points.txt
remote_detector-0.1.2.dist-info/top_level.txt
remote_detector-0.1.2.dist-info/RECORD
