Metadata-Version: 2.4
Name: remote-detector
Version: 0.1.2
Summary: Detects remote access tools and logs ERP login to MongoDB.
Home-page: https://github.com/yourusername/remote-detector
Author: Akshay Waghmare
Author-email: your.email@example.com
License: MIT
Project-URL: Bug Reports, https://github.com/yourusername/remote-detector/issues
Project-URL: Source, https://github.com/yourusername/remote-detector
Keywords: remote access,monitoring,security,erp,detection
Classifier: Development Status :: 4 - Beta
Classifier: Programming Language :: Python :: 3
Classifier: License :: OSI Approved :: MIT License
Classifier: Operating System :: MacOS
Classifier: Operating System :: POSIX :: Linux
Classifier: Operating System :: Microsoft :: Windows
Classifier: Intended Audience :: End Users/Desktop
Classifier: Topic :: Security
Classifier: Topic :: Utilities
Requires-Python: >=3.7
Requires-Dist: psutil
Requires-Dist: click
Requires-Dist: python-json-logger
Requires-Dist: requests
Requires-Dist: beautifulsoup4
Requires-Dist: pymongo
Dynamic: author
Dynamic: author-email
Dynamic: classifier
Dynamic: description
Dynamic: description-content-type
Dynamic: home-page
Dynamic: keywords
Dynamic: license
Dynamic: project-url
Dynamic: requires-dist
Dynamic: requires-python
Dynamic: summary
